swedish_dehyphenator/__init__.py
swedish_dehyphenator/config.py
swedish_dehyphenator/swedish_dehyphenator.py
swedish_dehyphenator-1.0.3.dist-info/LICENSE
swedish_dehyphenator-1.0.3.dist-info/METADATA
swedish_dehyphenator-1.0.3.dist-info/WHEEL
swedish_dehyphenator-1.0.3.dist-info/entry_points.txt
swedish_dehyphenator-1.0.3.dist-info/RECORD
