Metadata-Version: 2.1
Name: swedish-dehyphenator
Version: 1.0.3
Summary: A python program to remove end-line hyphenations from large texts.
Home-page: https://github.com/swerik-project/swedish-de-hyphenator/
License: GPLv3
Author: Stian Rødven Eide
Requires-Python: >=3.8,<4.0
Classifier: License :: Other/Proprietary License
Classifier: Programming Language :: Python :: 3
Classifier: Programming Language :: Python :: 3.8
Classifier: Programming Language :: Python :: 3.9
Classifier: Programming Language :: Python :: 3.10
Classifier: Programming Language :: Python :: 3.11
Classifier: Programming Language :: Python :: 3.12
Requires-Dist: getch
Requires-Dist: tqdm
Project-URL: Documentation, https://swerik-project.github.io/swedish-de-hyphenator/
Project-URL: Repository, https://github.com/swerik-project/swedish-de-hyphenator/
